orgm/__init__.py
orgm/__main__.py
orgm/comandos.md
orgm/menu.py
orgm/orgm.py
orgm/qstyle.py
orgm/adm/__init__.py
orgm/adm/pago.py
orgm/apps/__init__.py
orgm/apps/adm/__init__.py
orgm/apps/adm/db.py
orgm/apps/adm/cliente/__init__.py
orgm/apps/adm/cliente/app.py
orgm/apps/adm/cliente/edit_client.py
orgm/apps/adm/cliente/export_client.py
orgm/apps/adm/cliente/find_clients.py
orgm/apps/adm/cliente/form_client.py
orgm/apps/adm/cliente/get_client.py
orgm/apps/adm/cliente/get_clients.py
orgm/apps/adm/cliente/gui.py
orgm/apps/adm/cliente/max_id.py
orgm/apps/adm/cliente/menu.py
orgm/apps/adm/cliente/mostrar_export.py
orgm/apps/adm/cliente/new_client.py
orgm/apps/adm/cliente/tipos.py
orgm/apps/adm/cotizacion/__init__.py
orgm/apps/adm/cotizacion/app.py
orgm/apps/adm/cotizacion/ask_client.py
orgm/apps/adm/cotizacion/create_quotation.py
orgm/apps/adm/cotizacion/find_client.py
orgm/apps/adm/cotizacion/find_project.py
orgm/apps/adm/cotizacion/find_quotation.py
orgm/apps/adm/cotizacion/find_service.py
orgm/apps/adm/cotizacion/form_quotation.py
orgm/apps/adm/cotizacion/get_quotation.py
orgm/apps/adm/cotizacion/get_quotations.py
orgm/apps/adm/cotizacion/get_service.py
orgm/apps/adm/cotizacion/get_services.py
orgm/apps/adm/cotizacion/gui.py
orgm/apps/adm/cotizacion/max_id.py
orgm/apps/adm/cotizacion/menu.py
orgm/apps/adm/cotizacion/quotation_by_client.py
orgm/apps/adm/cotizacion/quotation_by_project.py
orgm/apps/adm/cotizacion/select_service.py
orgm/apps/adm/cotizacion/show_quotations.py
orgm/apps/adm/cotizacion/update_quotation.py
orgm/apps/adm/proyecto/__init__.py
orgm/apps/adm/proyecto/app.py
orgm/apps/adm/proyecto/create_project.py
orgm/apps/adm/proyecto/find_location.py
orgm/apps/adm/proyecto/find_project.py
orgm/apps/adm/proyecto/form_project.py
orgm/apps/adm/proyecto/get_project.py
orgm/apps/adm/proyecto/get_projects.py
orgm/apps/adm/proyecto/gui.py
orgm/apps/adm/proyecto/locations.py
orgm/apps/adm/proyecto/max_id.py
orgm/apps/adm/proyecto/menu.py
orgm-0.131.dist-info/licenses/LICENSE
orgm-0.131.dist-info/METADATA
orgm-0.131.dist-info/WHEEL
orgm-0.131.dist-info/entry_points.txt
orgm-0.131.dist-info/top_level.txt
orgm-0.131.dist-info/RECORD
