Metadata-Version: 2.4
Name: orgm
Version: 0.131
Summary: ORGM CLI for managing projects and tasks
Home-page: https://github.com/osmargm1202/cli.git
Author: Osmar Garcia
Author-email: osmargm1202@gmail.com
License-Expression: Apache-2.0
Project-URL: Homepage, https://github.com/osmargm1202/cli
Requires-Python: >=3.8
License-File: LICENSE
Requires-Dist: asciimatics>=1.15.0
Requires-Dist: click-repl>=0.3.0
Requires-Dist: docx-mailmerge>=0.5.0
Requires-Dist: docxcompose>=1.4.0
Requires-Dist: docxtpl>=0.20.0
Requires-Dist: kivy>=2.3.1
Requires-Dist: nicegui>=2.15.0
Requires-Dist: pypdf2>=3.0.1
Requires-Dist: pyperclip>=1.9.0
Requires-Dist: python-docx>=1.1.2
Requires-Dist: python-dotenv>=1.0.1
Requires-Dist: questionary>=2.1.0
Requires-Dist: reportlab>=4.4.0
Requires-Dist: requests>=2.32.3
Requires-Dist: rich>=13.9.4
Requires-Dist: setuptools>=75.3.2
Requires-Dist: sqlmodel>=0.0.24
Requires-Dist: textual>=0.73.0
Requires-Dist: typer>=0.15.2
Provides-Extra: test
Requires-Dist: pytest; extra == "test"
Dynamic: author-email
Dynamic: home-page
Dynamic: license-file
Dynamic: requires-python
